clipping.cpython-310-x86_64-linux-gnu.so
imputer.cpython-310-x86_64-linux-gnu.so
encoder.cpython-310-x86_64-linux-gnu.so
feature_gen.cpython-310-x86_64-linux-gnu.so
binning.cpython-310-x86_64-linux-gnu.so
feature_gen_dt.cpython-310-x86_64-linux-gnu.so
scaler.cpython-310-x86_64-linux-gnu.so
data_cleaning.cpython-310-x86_64-linux-gnu.so
feature_gen_str.cpython-310-x86_64-linux-gnu.so
gators-0.3.3.dist-info/METADATA
gators-0.3.3.dist-info/LICENSE
gators-0.3.3.dist-info/WHEEL
gators-0.3.3.dist-info/top_level.txt
gators-0.3.3.dist-info/RECORD
gators/__init__.py
gators/encoders/__init__.py
gators/encoders/target_encoder.py
gators/encoders/ordinal_encoder.py
gators/encoders/_base_encoder.py
gators/encoders/woe_encoder.py
gators/encoders/binned_columns_encoder.py
gators/encoders/encoder.pyx
gators/encoders/frequency_encoder.py
gators/encoders/onehot_encoder.py
gators/encoders/tests/test_target_encoder_pd.py
gators/encoders/tests/test_ordinal_encoder_dd.py
gators/encoders/tests/test_target_encoder_dd.py
gators/encoders/tests/test_ordinal_encoder_ks.py
gators/encoders/tests/test_woe_encoder_dd.py
gators/encoders/tests/test_binned_columns_encoder_ks.py
gators/encoders/tests/test_onehot_encoder_ks.py
gators/encoders/tests/test_onehot_encoder_dd.py
gators/encoders/tests/test_base_encoder.py
gators/encoders/tests/test_woe_encoder_pd.py
gators/encoders/tests/test_binned_columns_encoder_pd.py
gators/encoders/tests/test_woe_encoder_ks.py
gators/encoders/tests/test_onehot_encoder_pd.py
gators/encoders/tests/test_target_encoder_ks.py
gators/encoders/tests/test_frequency_encoder_pd.py
gators/encoders/tests/test_ordinal_encoder_pd.py
gators/encoders/tests/test_binned_columns_encoder_dd.py
gators/encoders/tests/__pycache__/test_regression_encoder.cpython-38-pytest-6.2.5.pyc
gators/encoders/tests/__pycache__/test_ordinal_encoder.cpython-36-pytest-6.2.5.pyc
gators/encoders/tests/__pycache__/test_target_encoder.cpython-37-pytest-6.2.5.pyc
gators/encoders/tests/__pycache__/test_ordinal_encoder.cpython-37-pytest-6.2.5.pyc
gators/encoders/tests/__pycache__/test_muticlass_encoder.cpython-36-pytest-6.2.5.pyc
