Metadata-Version: 2.1
Name: gators
Version: 0.3.3
Summary: Model building and model scoring library
Home-page: https://paypal.github.io/gators/
Author: The Gators Development Team
Maintainer: Charles Poli
License: License :: OSI Approved :: Apache Software License v2.0
Platform: UNKNOWN
Classifier: Programming Language :: Python :: 3
Classifier: Operating System :: OS Independent
Requires-Python: >=3.6
License-File: LICENSE
Requires-Dist: scikit-learn
Requires-Dist: seaborn
Requires-Dist: pandas (<=1.5.3)
Requires-Dist: lightgbm
Requires-Dist: xgboost
Requires-Dist: treelite
Requires-Dist: treelite-runtime
Requires-Dist: dill
Provides-Extra: dask
Requires-Dist: fsspec (>=0.3.3) ; extra == 'dask'
Requires-Dist: distributed ; extra == 'dask'
Requires-Dist: dask ; extra == 'dask'
Provides-Extra: dev
Requires-Dist: docutils (>=0.16.0) ; extra == 'dev'
Requires-Dist: pytest ; extra == 'dev'
Requires-Dist: pytest-cov ; extra == 'dev'
Requires-Dist: coverage ; extra == 'dev'
Requires-Dist: pylama (>=7.6.5) ; extra == 'dev'
Requires-Dist: jupyter ; extra == 'dev'
Requires-Dist: numpydoc ; extra == 'dev'
Requires-Dist: sphinx (>=3.3.0) ; extra == 'dev'
Requires-Dist: nbsphinx (>=0.8.0) ; extra == 'dev'
Requires-Dist: pydata-sphinx-theme ; extra == 'dev'
Requires-Dist: pandoc ; extra == 'dev'
Requires-Dist: tox ; extra == 'dev'
Requires-Dist: tox-wheel ; extra == 'dev'
Requires-Dist: black ; extra == 'dev'
Requires-Dist: isort ; extra == 'dev'
Requires-Dist: pyspark (<=3.1.3) ; extra == 'dev'
Requires-Dist: koalas ; extra == 'dev'
Requires-Dist: distributed ; extra == 'dev'
Requires-Dist: dask ; extra == 'dev'
Requires-Dist: numpy (<=1.23.5) ; extra == 'dev'
Provides-Extra: koalas
Requires-Dist: pyspark ; extra == 'koalas'
Requires-Dist: koalas ; extra == 'koalas'
